comparar_fundos_br/__init__.py
comparar_fundos_br/benchmarks.py
comparar_fundos_br/comparador.py
comparar_fundos_br/fundosbr.py
comparar_fundos_br/version.py
comparar_fundos_br-0.2.0.dist-info/METADATA
comparar_fundos_br-0.2.0.dist-info/WHEEL
comparar_fundos_br-0.2.0.dist-info/RECORD
