Metadata-Version: 2.3
Name: comparar_fundos_br
Version: 0.2.0
Summary: Obter dados de fundos de investimento
Author: Rafael Rodrigues
Author-email: rafael.rafarod@gmail.com
Requires-Python: >=3.10,<4.0
Classifier: Programming Language :: Python :: 3
Classifier: Programming Language :: Python :: 3.10
Classifier: Programming Language :: Python :: 3.11
Classifier: Programming Language :: Python :: 3.12
Classifier: Programming Language :: Python :: 3.13
Requires-Dist: fastexcel (>=0.13.0,<0.14.0)
Requires-Dist: matplotlib (>=3.10.0) ; python_version >= "3.10"
Requires-Dist: numpy (>=1.26.0) ; python_version >= "3.10"
Requires-Dist: pandas (>=2.1.0) ; python_version >= "3.10"
Requires-Dist: polars (>=1.27.1,<2.0.0)
Requires-Dist: pyarrow (==19.0.1)
Requires-Dist: pyettj (>=0.3.3) ; python_version >= "3.10"
Requires-Dist: requests (>=2.31,<3.0)
Requires-Dist: scipy (>=1.11.0) ; python_version >= "3.10"
Requires-Dist: yfinance (==0.2.59)
Project-URL: Homepage, https://github.com/rafa-rod/comparar_fundos_br.git
